pynverse/__init__.py
pynverse/inverse.py
pynverse/utils.py
pynverse/version.py
pynverse-0.1.4.6.dist-info/LICENSE.txt
pynverse-0.1.4.6.dist-info/METADATA
pynverse-0.1.4.6.dist-info/WHEEL
pynverse-0.1.4.6.dist-info/top_level.txt
pynverse-0.1.4.6.dist-info/RECORD
